pywellen/__init__.py
pywellen/pywellen.cpython-312-darwin.so
pywellen/pywellen.pyi
pywellen-0.20.2.dist-info/METADATA
pywellen-0.20.2.dist-info/WHEEL
pywellen-0.20.2.dist-info/RECORD
