Metadata-Version: 2.4
Name: pywellen
Version: 0.20.2
Classifier: Programming Language :: Rust
Classifier: Programming Language :: Python :: Implementation :: CPython
Classifier: Programming Language :: Python :: Implementation :: PyPy
Classifier: Topic :: Scientific/Engineering
Classifier: Topic :: Scientific/Engineering :: Electronic Design Automation (EDA)
Summary: Fast VCD, GHW and FST wavedump reading.
Author-email: James Connolly <dogman3117@gmail.com>, Kevin Laeufer <laeufer@cornell.edu>
License-Expression: BSD-3-Clause
Requires-Python: >=3.9
Project-URL: Homepage, https://github.com/ekiwi/wellen
Project-URL: Issues, https://github.com/ekiwi/wellen/issues
